cache_tools/__init__.py
cache_tools/conf.py
cache_tools/fields.py
cache_tools/utils.py
dj_cache_tools-0.6.3.dist-info/DESCRIPTION.rst
dj_cache_tools-0.6.3.dist-info/METADATA
dj_cache_tools-0.6.3.dist-info/RECORD
dj_cache_tools-0.6.3.dist-info/WHEEL
dj_cache_tools-0.6.3.dist-info/metadata.json
dj_cache_tools-0.6.3.dist-info/top_level.txt
